pytq/__init__.py
pytq/__init__.pyc
pytq/per_class_logger.py
pytq/per_class_logger.pyc
pytq/scheduler.py
pytq/scheduler.pyc
pytq/scheduler_mongodb.py
pytq/scheduler_mongodb.pyc
pytq/scheduler_mongodb_status_flag.py
pytq/scheduler_mongodb_status_flag.pyc
pytq/scheduler_sql.py
pytq/scheduler_sql.pyc
pytq/scheduler_sql_status_flag.py
pytq/scheduler_sql_status_flag.pyc
pytq/scheduler_sqlitedict.py
pytq/scheduler_sqlitedict.pyc
pytq/task.py
pytq/task.pyc
pytq/pkg/__init__.py
pytq/pkg/__init__.pyc
pytq/pkg/exception_mate.py
pytq/pkg/exception_mate.pyc
pytq/pkg/fingerprint.py
pytq/pkg/fingerprint.pyc
pytq/pkg/sixmini.py
pytq/pkg/sqlitedict.py
pytq/pkg/sqlitedict.pyc
pytq/pkg/attrs_mate/__init__.py
pytq/pkg/attrs_mate/__init__.pyc
pytq/pkg/attrs_mate/mate.py
pytq/pkg/attrs_mate/mate.pyc
pytq/pkg/loggerFactory/__init__.py
pytq/pkg/loggerFactory/__init__.pyc
pytq/pkg/loggerFactory/logfilter.py
pytq/pkg/loggerFactory/logfilter.pyc
pytq/pkg/loggerFactory/logger.py
pytq/pkg/loggerFactory/logger.pyc
pytq-0.0.7.dist-info/DESCRIPTION.rst
pytq-0.0.7.dist-info/METADATA
pytq-0.0.7.dist-info/RECORD
pytq-0.0.7.dist-info/WHEEL
pytq-0.0.7.dist-info/metadata.json
pytq-0.0.7.dist-info/top_level.txt
